{"name":"Check if User can update  employees in the application","id":"testing-different-products-on-the-best-api-application:Check if User can update  employees in the application","testSteps":[{"number":1,"description":"Given I am on Homepage of application DummyApi","duration":2,"startTime":"2022-06-20T21:58:18.217+01:00[Europe/London]","result":"SUCCESS","precondition":false},{"number":2,"description":"When User can create new employee using PUT method in employees application","duration":61,"startTime":"2022-06-20T21:58:18.219+01:00[Europe/London]","exception":{"errorType":"java.lang.IllegalArgumentException","message":"Invalid number of path parameters. Expected 1, was 0. Undefined path parameters are: employeeID.","stackTrace":[{"declaringClass":"io.restassured.internal.RequestSpecificationImpl","methodName":"assertCorrectNumberOfPathParams","fileName":"RequestSpecificationImpl.groovy","lineNumber":1336},{"declaringClass":"groovy.lang.MetaMethod","methodName":"doMethodInvoke","fileName":"MetaMethod.java","lineNumber":325},{"declaringClass":"groovy.lang.MetaClassImpl","methodName":"invokeMethod","fileName":"MetaClassImpl.java","lineNumber":1213},{"declaringClass":"groovy.lang.MetaClassImpl","methodName":"invokeMethod","fileName":"MetaClassImpl.java","lineNumber":1022},{"declaringClass":"groovy.lang.MetaClassImpl","methodName":"invokeMethod","fileName":"MetaClassImpl.java","lineNumber":810},{"declaringClass":"io.restassured.internal.RequestSpecificationImpl","methodName":"invokeMethod","fileName":"RequestSpecificationImpl.groovy","lineNumber":-1},{"declaringClass":"io.restassured.internal.RequestSpecificationImpl","methodName":"sendRequest","fileName":"RequestSpecificationImpl.groovy","lineNumber":1223},{"declaringClass":"groovy.lang.MetaMethod","methodName":"doMethodInvoke","fileName":"MetaMethod.java","lineNumber":325},{"declaringClass":"groovy.lang.MetaClassImpl","methodName":"invokeMethod","fileName":"MetaClassImpl.java","lineNumber":1213},{"declaringClass":"groovy.lang.MetaClassImpl","methodName":"invokeMethod","fileName":"MetaClassImpl.java","lineNumber":1022},{"declaringClass":"groovy.lang.MetaClassImpl","methodName":"invokeMethod","fileName":"MetaClassImpl.java","lineNumber":810},{"declaringClass":"io.restassured.internal.RequestSpecificationImpl","methodName":"invokeMethod","fileName":"RequestSpecificationImpl.groovy","lineNumber":-1},{"declaringClass":"io.restassured.internal.filter.SendRequestFilter","methodName":"filter","fileName":"SendRequestFilter.groovy","lineNumber":30},{"declaringClass":"io.restassured.internal.filter.FilterContextImpl","methodName":"next","fileName":"FilterContextImpl.groovy","lineNumber":72},{"declaringClass":"io.restassured.filter.time.TimingFilter","methodName":"filter","fileName":"TimingFilter.java","lineNumber":56},{"declaringClass":"io.restassured.internal.filter.FilterContextImpl","methodName":"next","fileName":"FilterContextImpl.groovy","lineNumber":72},{"declaringClass":"io.restassured.filter.log.RequestLoggingFilter","methodName":"filter","fileName":"RequestLoggingFilter.java","lineNumber":124},{"declaringClass":"io.restassured.internal.filter.FilterContextImpl","methodName":"next","fileName":"FilterContextImpl.groovy","lineNumber":72},{"declaringClass":"io.restassured.filter.log.RequestLoggingFilter","methodName":"filter","fileName":"RequestLoggingFilter.java","lineNumber":124},{"declaringClass":"net.serenitybdd.rest.filters.FieldsRecordingFilter","methodName":"filter","fileName":"FieldsRecordingFilter.java","lineNumber":40},{"declaringClass":"io.restassured.internal.filter.FilterContextImpl","methodName":"next","fileName":"FilterContextImpl.groovy","lineNumber":72},{"declaringClass":"io.restassured.filter.log.RequestLoggingFilter","methodName":"filter","fileName":"RequestLoggingFilter.java","lineNumber":124},{"declaringClass":"net.serenitybdd.rest.filters.FieldsRecordingFilter","methodName":"filter","fileName":"FieldsRecordingFilter.java","lineNumber":40},{"declaringClass":"io.restassured.internal.filter.FilterContextImpl","methodName":"next","fileName":"FilterContextImpl.groovy","lineNumber":72},{"declaringClass":"io.restassured.filter.log.RequestLoggingFilter","methodName":"filter","fileName":"RequestLoggingFilter.java","lineNumber":124},{"declaringClass":"net.serenitybdd.rest.filters.FieldsRecordingFilter","methodName":"filter","fileName":"FieldsRecordingFilter.java","lineNumber":40},{"declaringClass":"io.restassured.internal.filter.FilterContextImpl","methodName":"next","fileName":"FilterContextImpl.groovy","lineNumber":72},{"declaringClass":"io.restassured.filter.log.RequestLoggingFilter","methodName":"filter","fileName":"RequestLoggingFilter.java","lineNumber":124},{"declaringClass":"net.serenitybdd.rest.filters.FieldsRecordingFilter","methodName":"filter","fileName":"FieldsRecordingFilter.java","lineNumber":40},{"declaringClass":"io.restassured.internal.filter.FilterContextImpl","methodName":"next","fileName":"FilterContextImpl.groovy","lineNumber":72},{"declaringClass":"io.restassured.filter.log.RequestLoggingFilter","methodName":"filter","fileName":"RequestLoggingFilter.java","lineNumber":124},{"declaringClass":"net.serenitybdd.rest.filters.FieldsRecordingFilter","methodName":"filter","fileName":"FieldsRecordingFilter.java","lineNumber":40},{"declaringClass":"io.restassured.internal.filter.FilterContextImpl","methodName":"next","fileName":"FilterContextImpl.groovy","lineNumber":72},{"declaringClass":"io.restassured.filter.log.RequestLoggingFilter","methodName":"filter","fileName":"RequestLoggingFilter.java","lineNumber":124},{"declaringClass":"net.serenitybdd.rest.filters.FieldsRecordingFilter","methodName":"filter","fileName":"FieldsRecordingFilter.java","lineNumber":40},{"declaringClass":"io.restassured.internal.filter.FilterContextImpl","methodName":"next","fileName":"FilterContextImpl.groovy","lineNumber":72},{"declaringClass":"io.restassured.internal.RequestSpecificationImpl","methodName":"applyPathParamsAndSendRequest","fileName":"RequestSpecificationImpl.groovy","lineNumber":1722},{"declaringClass":"groovy.lang.MetaMethod","methodName":"doMethodInvoke","fileName":"MetaMethod.java","lineNumber":325},{"declaringClass":"groovy.lang.MetaClassImpl","methodName":"invokeMethod","fileName":"MetaClassImpl.java","lineNumber":1213},{"declaringClass":"groovy.lang.MetaClassImpl","methodName":"invokeMethod","fileName":"MetaClassImpl.java","lineNumber":1022},{"declaringClass":"groovy.lang.MetaClassImpl","methodName":"invokeMethod","fileName":"MetaClassImpl.java","lineNumber":810},{"declaringClass":"io.restassured.internal.RequestSpecificationImpl","methodName":"invokeMethod","fileName":"RequestSpecificationImpl.groovy","lineNumber":-1},{"declaringClass":"io.restassured.internal.RequestSpecificationImpl","methodName":"applyPathParamsAndSendRequest","fileName":"RequestSpecificationImpl.groovy","lineNumber":1728},{"declaringClass":"groovy.lang.MetaMethod","methodName":"doMethodInvoke","fileName":"MetaMethod.java","lineNumber":325},{"declaringClass":"groovy.lang.MetaClassImpl","methodName":"invokeMethod","fileName":"MetaClassImpl.java","lineNumber":1213},{"declaringClass":"groovy.lang.MetaClassImpl","methodName":"invokeMethod","fileName":"MetaClassImpl.java","lineNumber":1022},{"declaringClass":"groovy.lang.MetaClassImpl","methodName":"invokeMethod","fileName":"MetaClassImpl.java","lineNumber":810},{"declaringClass":"io.restassured.internal.RequestSpecificationImpl","methodName":"invokeMethod","fileName":"RequestSpecificationImpl.groovy","lineNumber":-1},{"declaringClass":"io.restassured.internal.RequestSpecificationImpl","methodName":"post","fileName":"RequestSpecificationImpl.groovy","lineNumber":172},{"declaringClass":"net.serenitybdd.rest.decorators.request.RequestSpecificationDecorated","methodName":"execute","fileName":"RequestSpecificationDecorated.java","lineNumber":224},{"declaringClass":"net.serenitybdd.rest.decorators.request.RequestSpecificationDecorated","methodName":"post","fileName":"RequestSpecificationDecorated.java","lineNumber":74},{"declaringClass":"net.serenitybdd.rest.decorators.request.RequestSpecificationDecorated","methodName":"post","fileName":"RequestSpecificationDecorated.java","lineNumber":27},{"declaringClass":"com.restapiexample.dummy.dummyinfosteps.DummySteps","methodName":"updateDummy","fileName":"DummySteps.java","lineNumber":69},{"declaringClass":"com.restapiexample.dummy.cucumber.MyStepdefs","methodName":"userCanCreateNewEmployeeUsingPUTMethodInEmployeesApplication","fileName":"MyStepdefs.java","lineNumber":65},{"declaringClass":"✽","methodName":"When User can create new employee using PUT method in employees application","fileName":"Productinfo.feature","lineNumber":15}]},"result":"ERROR","precondition":false,"children":[{"number":3,"description":"Update dummy: Employee48657_updated, Employee82714, 40, 1234, Employee62567, 25000, 42, Employee24084, {Marks\u003d8, Gentleman\u003d10}","duration":49,"startTime":"2022-06-20T21:58:18.220+01:00[Europe/London]","exception":{"errorType":"java.lang.IllegalArgumentException","message":"Invalid number of path parameters. Expected 1, was 0. Undefined path parameters are: employeeID.","stackTrace":[{"declaringClass":"io.restassured.internal.RequestSpecificationImpl","methodName":"assertCorrectNumberOfPathParams","fileName":"RequestSpecificationImpl.groovy","lineNumber":1336},{"declaringClass":"groovy.lang.MetaMethod","methodName":"doMethodInvoke","fileName":"MetaMethod.java","lineNumber":325},{"declaringClass":"groovy.lang.MetaClassImpl","methodName":"invokeMethod","fileName":"MetaClassImpl.java","lineNumber":1213},{"declaringClass":"groovy.lang.MetaClassImpl","methodName":"invokeMethod","fileName":"MetaClassImpl.java","lineNumber":1022},{"declaringClass":"groovy.lang.MetaClassImpl","methodName":"invokeMethod","fileName":"MetaClassImpl.java","lineNumber":810},{"declaringClass":"io.restassured.internal.RequestSpecificationImpl","methodName":"invokeMethod","fileName":"RequestSpecificationImpl.groovy","lineNumber":-1},{"declaringClass":"io.restassured.internal.RequestSpecificationImpl","methodName":"sendRequest","fileName":"RequestSpecificationImpl.groovy","lineNumber":1223},{"declaringClass":"groovy.lang.MetaMethod","methodName":"doMethodInvoke","fileName":"MetaMethod.java","lineNumber":325},{"declaringClass":"groovy.lang.MetaClassImpl","methodName":"invokeMethod","fileName":"MetaClassImpl.java","lineNumber":1213},{"declaringClass":"groovy.lang.MetaClassImpl","methodName":"invokeMethod","fileName":"MetaClassImpl.java","lineNumber":1022},{"declaringClass":"groovy.lang.MetaClassImpl","methodName":"invokeMethod","fileName":"MetaClassImpl.java","lineNumber":810},{"declaringClass":"io.restassured.internal.RequestSpecificationImpl","methodName":"invokeMethod","fileName":"RequestSpecificationImpl.groovy","lineNumber":-1},{"declaringClass":"io.restassured.internal.filter.SendRequestFilter","methodName":"filter","fileName":"SendRequestFilter.groovy","lineNumber":30},{"declaringClass":"io.restassured.internal.filter.FilterContextImpl","methodName":"next","fileName":"FilterContextImpl.groovy","lineNumber":72},{"declaringClass":"io.restassured.filter.time.TimingFilter","methodName":"filter","fileName":"TimingFilter.java","lineNumber":56},{"declaringClass":"io.restassured.internal.filter.FilterContextImpl","methodName":"next","fileName":"FilterContextImpl.groovy","lineNumber":72},{"declaringClass":"io.restassured.filter.log.RequestLoggingFilter","methodName":"filter","fileName":"RequestLoggingFilter.java","lineNumber":124},{"declaringClass":"io.restassured.internal.filter.FilterContextImpl","methodName":"next","fileName":"FilterContextImpl.groovy","lineNumber":72},{"declaringClass":"io.restassured.filter.log.RequestLoggingFilter","methodName":"filter","fileName":"RequestLoggingFilter.java","lineNumber":124},{"declaringClass":"net.serenitybdd.rest.filters.FieldsRecordingFilter","methodName":"filter","fileName":"FieldsRecordingFilter.java","lineNumber":40},{"declaringClass":"io.restassured.internal.filter.FilterContextImpl","methodName":"next","fileName":"FilterContextImpl.groovy","lineNumber":72},{"declaringClass":"io.restassured.filter.log.RequestLoggingFilter","methodName":"filter","fileName":"RequestLoggingFilter.java","lineNumber":124},{"declaringClass":"net.serenitybdd.rest.filters.FieldsRecordingFilter","methodName":"filter","fileName":"FieldsRecordingFilter.java","lineNumber":40},{"declaringClass":"io.restassured.internal.filter.FilterContextImpl","methodName":"next","fileName":"FilterContextImpl.groovy","lineNumber":72},{"declaringClass":"io.restassured.filter.log.RequestLoggingFilter","methodName":"filter","fileName":"RequestLoggingFilter.java","lineNumber":124},{"declaringClass":"net.serenitybdd.rest.filters.FieldsRecordingFilter","methodName":"filter","fileName":"FieldsRecordingFilter.java","lineNumber":40},{"declaringClass":"io.restassured.internal.filter.FilterContextImpl","methodName":"next","fileName":"FilterContextImpl.groovy","lineNumber":72},{"declaringClass":"io.restassured.filter.log.RequestLoggingFilter","methodName":"filter","fileName":"RequestLoggingFilter.java","lineNumber":124},{"declaringClass":"net.serenitybdd.rest.filters.FieldsRecordingFilter","methodName":"filter","fileName":"FieldsRecordingFilter.java","lineNumber":40},{"declaringClass":"io.restassured.internal.filter.FilterContextImpl","methodName":"next","fileName":"FilterContextImpl.groovy","lineNumber":72},{"declaringClass":"io.restassured.filter.log.RequestLoggingFilter","methodName":"filter","fileName":"RequestLoggingFilter.java","lineNumber":124},{"declaringClass":"net.serenitybdd.rest.filters.FieldsRecordingFilter","methodName":"filter","fileName":"FieldsRecordingFilter.java","lineNumber":40},{"declaringClass":"io.restassured.internal.filter.FilterContextImpl","methodName":"next","fileName":"FilterContextImpl.groovy","lineNumber":72},{"declaringClass":"io.restassured.filter.log.RequestLoggingFilter","methodName":"filter","fileName":"RequestLoggingFilter.java","lineNumber":124},{"declaringClass":"net.serenitybdd.rest.filters.FieldsRecordingFilter","methodName":"filter","fileName":"FieldsRecordingFilter.java","lineNumber":40},{"declaringClass":"io.restassured.internal.filter.FilterContextImpl","methodName":"next","fileName":"FilterContextImpl.groovy","lineNumber":72},{"declaringClass":"io.restassured.internal.RequestSpecificationImpl","methodName":"applyPathParamsAndSendRequest","fileName":"RequestSpecificationImpl.groovy","lineNumber":1722},{"declaringClass":"groovy.lang.MetaMethod","methodName":"doMethodInvoke","fileName":"MetaMethod.java","lineNumber":325},{"declaringClass":"groovy.lang.MetaClassImpl","methodName":"invokeMethod","fileName":"MetaClassImpl.java","lineNumber":1213},{"declaringClass":"groovy.lang.MetaClassImpl","methodName":"invokeMethod","fileName":"MetaClassImpl.java","lineNumber":1022},{"declaringClass":"groovy.lang.MetaClassImpl","methodName":"invokeMethod","fileName":"MetaClassImpl.java","lineNumber":810},{"declaringClass":"io.restassured.internal.RequestSpecificationImpl","methodName":"invokeMethod","fileName":"RequestSpecificationImpl.groovy","lineNumber":-1},{"declaringClass":"io.restassured.internal.RequestSpecificationImpl","methodName":"applyPathParamsAndSendRequest","fileName":"RequestSpecificationImpl.groovy","lineNumber":1728},{"declaringClass":"groovy.lang.MetaMethod","methodName":"doMethodInvoke","fileName":"MetaMethod.java","lineNumber":325},{"declaringClass":"groovy.lang.MetaClassImpl","methodName":"invokeMethod","fileName":"MetaClassImpl.java","lineNumber":1213},{"declaringClass":"groovy.lang.MetaClassImpl","methodName":"invokeMethod","fileName":"MetaClassImpl.java","lineNumber":1022},{"declaringClass":"groovy.lang.MetaClassImpl","methodName":"invokeMethod","fileName":"MetaClassImpl.java","lineNumber":810},{"declaringClass":"io.restassured.internal.RequestSpecificationImpl","methodName":"invokeMethod","fileName":"RequestSpecificationImpl.groovy","lineNumber":-1},{"declaringClass":"io.restassured.internal.RequestSpecificationImpl","methodName":"post","fileName":"RequestSpecificationImpl.groovy","lineNumber":172},{"declaringClass":"net.serenitybdd.rest.decorators.request.RequestSpecificationDecorated","methodName":"execute","fileName":"RequestSpecificationDecorated.java","lineNumber":224},{"declaringClass":"net.serenitybdd.rest.decorators.request.RequestSpecificationDecorated","methodName":"post","fileName":"RequestSpecificationDecorated.java","lineNumber":74},{"declaringClass":"net.serenitybdd.rest.decorators.request.RequestSpecificationDecorated","methodName":"post","fileName":"RequestSpecificationDecorated.java","lineNumber":27},{"declaringClass":"com.restapiexample.dummy.dummyinfosteps.DummySteps","methodName":"updateDummy","fileName":"DummySteps.java","lineNumber":69},{"declaringClass":"com.restapiexample.dummy.cucumber.MyStepdefs","methodName":"userCanCreateNewEmployeeUsingPUTMethodInEmployeesApplication","fileName":"MyStepdefs.java","lineNumber":65}]},"result":"ERROR","precondition":false}]},{"number":4,"description":"Then User can get back a valid status code 200 of employees","duration":1,"startTime":"2022-06-20T21:58:18.281+01:00[Europe/London]","result":"SKIPPED","precondition":false}],"userStory":{"id":"testing-different-products-on-the-best-api-application","storyName":"Testing different products on the Best Api Application","path":"Productinfo.feature","type":"feature"},"featureTag":{"name":"Testing different products on the Best Api Application","type":"feature"},"title":"Check if User can update  employees in the application","description":"","tags":[{"name":"Testing different products on the Best Api Application","type":"feature"}],"startTime":"2022-06-20T21:58:18.215+01:00[Europe/London]","duration":67,"testFailureCause":{"errorType":"java.lang.IllegalArgumentException","message":"Invalid number of path parameters. Expected 1, was 0. Undefined path parameters are: employeeID.","stackTrace":[{"declaringClass":"io.restassured.internal.RequestSpecificationImpl","methodName":"assertCorrectNumberOfPathParams","fileName":"RequestSpecificationImpl.groovy","lineNumber":1336},{"declaringClass":"groovy.lang.MetaMethod","methodName":"doMethodInvoke","fileName":"MetaMethod.java","lineNumber":325},{"declaringClass":"groovy.lang.MetaClassImpl","methodName":"invokeMethod","fileName":"MetaClassImpl.java","lineNumber":1213},{"declaringClass":"groovy.lang.MetaClassImpl","methodName":"invokeMethod","fileName":"MetaClassImpl.java","lineNumber":1022},{"declaringClass":"groovy.lang.MetaClassImpl","methodName":"invokeMethod","fileName":"MetaClassImpl.java","lineNumber":810},{"declaringClass":"io.restassured.internal.RequestSpecificationImpl","methodName":"invokeMethod","fileName":"RequestSpecificationImpl.groovy","lineNumber":-1},{"declaringClass":"io.restassured.internal.RequestSpecificationImpl","methodName":"sendRequest","fileName":"RequestSpecificationImpl.groovy","lineNumber":1223},{"declaringClass":"groovy.lang.MetaMethod","methodName":"doMethodInvoke","fileName":"MetaMethod.java","lineNumber":325},{"declaringClass":"groovy.lang.MetaClassImpl","methodName":"invokeMethod","fileName":"MetaClassImpl.java","lineNumber":1213},{"declaringClass":"groovy.lang.MetaClassImpl","methodName":"invokeMethod","fileName":"MetaClassImpl.java","lineNumber":1022},{"declaringClass":"groovy.lang.MetaClassImpl","methodName":"invokeMethod","fileName":"MetaClassImpl.java","lineNumber":810},{"declaringClass":"io.restassured.internal.RequestSpecificationImpl","methodName":"invokeMethod","fileName":"RequestSpecificationImpl.groovy","lineNumber":-1},{"declaringClass":"io.restassured.internal.filter.SendRequestFilter","methodName":"filter","fileName":"SendRequestFilter.groovy","lineNumber":30},{"declaringClass":"io.restassured.internal.filter.FilterContextImpl","methodName":"next","fileName":"FilterContextImpl.groovy","lineNumber":72},{"declaringClass":"io.restassured.filter.time.TimingFilter","methodName":"filter","fileName":"TimingFilter.java","lineNumber":56},{"declaringClass":"io.restassured.internal.filter.FilterContextImpl","methodName":"next","fileName":"FilterContextImpl.groovy","lineNumber":72},{"declaringClass":"io.restassured.filter.log.RequestLoggingFilter","methodName":"filter","fileName":"RequestLoggingFilter.java","lineNumber":124},{"declaringClass":"io.restassured.internal.filter.FilterContextImpl","methodName":"next","fileName":"FilterContextImpl.groovy","lineNumber":72},{"declaringClass":"io.restassured.filter.log.RequestLoggingFilter","methodName":"filter","fileName":"RequestLoggingFilter.java","lineNumber":124},{"declaringClass":"net.serenitybdd.rest.filters.FieldsRecordingFilter","methodName":"filter","fileName":"FieldsRecordingFilter.java","lineNumber":40},{"declaringClass":"io.restassured.internal.filter.FilterContextImpl","methodName":"next","fileName":"FilterContextImpl.groovy","lineNumber":72},{"declaringClass":"io.restassured.filter.log.RequestLoggingFilter","methodName":"filter","fileName":"RequestLoggingFilter.java","lineNumber":124},{"declaringClass":"net.serenitybdd.rest.filters.FieldsRecordingFilter","methodName":"filter","fileName":"FieldsRecordingFilter.java","lineNumber":40},{"declaringClass":"io.restassured.internal.filter.FilterContextImpl","methodName":"next","fileName":"FilterContextImpl.groovy","lineNumber":72},{"declaringClass":"io.restassured.filter.log.RequestLoggingFilter","methodName":"filter","fileName":"RequestLoggingFilter.java","lineNumber":124},{"declaringClass":"net.serenitybdd.rest.filters.FieldsRecordingFilter","methodName":"filter","fileName":"FieldsRecordingFilter.java","lineNumber":40},{"declaringClass":"io.restassured.internal.filter.FilterContextImpl","methodName":"next","fileName":"FilterContextImpl.groovy","lineNumber":72},{"declaringClass":"io.restassured.filter.log.RequestLoggingFilter","methodName":"filter","fileName":"RequestLoggingFilter.java","lineNumber":124},{"declaringClass":"net.serenitybdd.rest.filters.FieldsRecordingFilter","methodName":"filter","fileName":"FieldsRecordingFilter.java","lineNumber":40},{"declaringClass":"io.restassured.internal.filter.FilterContextImpl","methodName":"next","fileName":"FilterContextImpl.groovy","lineNumber":72},{"declaringClass":"io.restassured.filter.log.RequestLoggingFilter","methodName":"filter","fileName":"RequestLoggingFilter.java","lineNumber":124},{"declaringClass":"net.serenitybdd.rest.filters.FieldsRecordingFilter","methodName":"filter","fileName":"FieldsRecordingFilter.java","lineNumber":40},{"declaringClass":"io.restassured.internal.filter.FilterContextImpl","methodName":"next","fileName":"FilterContextImpl.groovy","lineNumber":72},{"declaringClass":"io.restassured.filter.log.RequestLoggingFilter","methodName":"filter","fileName":"RequestLoggingFilter.java","lineNumber":124},{"declaringClass":"net.serenitybdd.rest.filters.FieldsRecordingFilter","methodName":"filter","fileName":"FieldsRecordingFilter.java","lineNumber":40},{"declaringClass":"io.restassured.internal.filter.FilterContextImpl","methodName":"next","fileName":"FilterContextImpl.groovy","lineNumber":72},{"declaringClass":"io.restassured.internal.RequestSpecificationImpl","methodName":"applyPathParamsAndSendRequest","fileName":"RequestSpecificationImpl.groovy","lineNumber":1722},{"declaringClass":"groovy.lang.MetaMethod","methodName":"doMethodInvoke","fileName":"MetaMethod.java","lineNumber":325},{"declaringClass":"groovy.lang.MetaClassImpl","methodName":"invokeMethod","fileName":"MetaClassImpl.java","lineNumber":1213},{"declaringClass":"groovy.lang.MetaClassImpl","methodName":"invokeMethod","fileName":"MetaClassImpl.java","lineNumber":1022},{"declaringClass":"groovy.lang.MetaClassImpl","methodName":"invokeMethod","fileName":"MetaClassImpl.java","lineNumber":810},{"declaringClass":"io.restassured.internal.RequestSpecificationImpl","methodName":"invokeMethod","fileName":"RequestSpecificationImpl.groovy","lineNumber":-1},{"declaringClass":"io.restassured.internal.RequestSpecificationImpl","methodName":"applyPathParamsAndSendRequest","fileName":"RequestSpecificationImpl.groovy","lineNumber":1728},{"declaringClass":"groovy.lang.MetaMethod","methodName":"doMethodInvoke","fileName":"MetaMethod.java","lineNumber":325},{"declaringClass":"groovy.lang.MetaClassImpl","methodName":"invokeMethod","fileName":"MetaClassImpl.java","lineNumber":1213},{"declaringClass":"groovy.lang.MetaClassImpl","methodName":"invokeMethod","fileName":"MetaClassImpl.java","lineNumber":1022},{"declaringClass":"groovy.lang.MetaClassImpl","methodName":"invokeMethod","fileName":"MetaClassImpl.java","lineNumber":810},{"declaringClass":"io.restassured.internal.RequestSpecificationImpl","methodName":"invokeMethod","fileName":"RequestSpecificationImpl.groovy","lineNumber":-1},{"declaringClass":"io.restassured.internal.RequestSpecificationImpl","methodName":"post","fileName":"RequestSpecificationImpl.groovy","lineNumber":172},{"declaringClass":"net.serenitybdd.rest.decorators.request.RequestSpecificationDecorated","methodName":"execute","fileName":"RequestSpecificationDecorated.java","lineNumber":224},{"declaringClass":"net.serenitybdd.rest.decorators.request.RequestSpecificationDecorated","methodName":"post","fileName":"RequestSpecificationDecorated.java","lineNumber":74},{"declaringClass":"net.serenitybdd.rest.decorators.request.RequestSpecificationDecorated","methodName":"post","fileName":"RequestSpecificationDecorated.java","lineNumber":27},{"declaringClass":"com.restapiexample.dummy.dummyinfosteps.DummySteps","methodName":"updateDummy","fileName":"DummySteps.java","lineNumber":69},{"declaringClass":"com.restapiexample.dummy.cucumber.MyStepdefs","methodName":"userCanCreateNewEmployeeUsingPUTMethodInEmployeesApplication","fileName":"MyStepdefs.java","lineNumber":65}]},"testFailureClassname":"java.lang.IllegalArgumentException","testFailureMessage":"Invalid number of path parameters. Expected 1, was 0. Undefined path parameters are: employeeID.","testFailureSummary":"ERROR;java.lang.IllegalArgumentException;Invalid number of path parameters. Expected 1, was 0. Undefined path parameters are: employeeID.;RequestSpecificationImpl.groovy","projectKey":"","annotatedResult":"ERROR","manual":false,"result":"ERROR"}